gitlab_management/__init__.py
gitlab_management/__main__.py
gitlab_management/base.py
gitlab_management/cli.py
test/__init__.py
test/test_function.py
test/test_integration.py
test/test_unit.py
gitlab_management-0.2.1.dist-info/LICENSE
gitlab_management-0.2.1.dist-info/METADATA
gitlab_management-0.2.1.dist-info/WHEEL
gitlab_management-0.2.1.dist-info/entry_points.txt
gitlab_management-0.2.1.dist-info/top_level.txt
gitlab_management-0.2.1.dist-info/RECORD
