Metadata-Version: 2.1
Name: gitlab-management
Version: 0.2.1
Summary: GitLab group configuration as code
Home-page: https://gitlab.com/nofusscomputing/projects/python-gitlab-management
Author: NoFussComputing
Author-email: helpdesk@nofusscomputing.com
License: UNKNOWN
Project-URL: Bug Tracker, https://gitlab.com/nofusscomputing/projects/python-gitlab-management/-/issues
Project-URL: Documentation, https://python-gitlab-management.readthedocs.io/
Project-URL: Source Code, https://gitlab.com/nofusscomputing/projects/python-gitlab-management/-/tree/7459ee62f53bb39419a11a5c632a15db35f05985
Platform: UNKNOWN
Classifier: Programming Language :: Python :: 3
Classifier: Operating System :: OS Independent
Requires-Python: >=3.6
Requires-Dist: GitPython (==3.1.3)
Requires-Dist: python-gitlab (==2.2.0)
Requires-Dist: PyYAML (==5.3.1)
